efb_wechat_basic_slave/Helper.py
efb_wechat_basic_slave/__init__.py
efb_wechat_basic_slave/__version__.py
efb_wechat_basic_slave-0.0.2.dist-info/METADATA
efb_wechat_basic_slave-0.0.2.dist-info/RECORD
efb_wechat_basic_slave-0.0.2.dist-info/WHEEL
efb_wechat_basic_slave-0.0.2.dist-info/entry_points.txt
efb_wechat_basic_slave-0.0.2.dist-info/top_level.txt
